helloworld.py
helloworld_bvd-0.0.1.dist-info/LICENSE.txt
helloworld_bvd-0.0.1.dist-info/METADATA
helloworld_bvd-0.0.1.dist-info/WHEEL
helloworld_bvd-0.0.1.dist-info/top_level.txt
helloworld_bvd-0.0.1.dist-info/RECORD
